tno/quantum/ml/regression/linear_regression/__init__.py
tno/quantum/ml/regression/linear_regression/_estimator.py
tno/quantum/ml/regression/linear_regression/_quantum_inspired.py
tno/quantum/ml/regression/linear_regression/_sketching.py
tno/quantum/ml/regression/linear_regression/py.typed
tno/quantum/ml/regression/linear_regression/test/__init__.py
tno/quantum/ml/regression/linear_regression/test/test_estimator.py
tno/quantum/ml/regression/linear_regression/test/test_quantum_inspired.py
tno/quantum/ml/regression/linear_regression/test/test_sketching.py
tno_quantum_ml_regression_linear_regression-1.0.0.dist-info/licenses/LICENSE
tno_quantum_ml_regression_linear_regression-1.0.0.dist-info/METADATA
tno_quantum_ml_regression_linear_regression-1.0.0.dist-info/WHEEL
tno_quantum_ml_regression_linear_regression-1.0.0.dist-info/top_level.txt
tno_quantum_ml_regression_linear_regression-1.0.0.dist-info/RECORD
